torch_hog/__init__.py
torch_hog/functional.py
torch_hog/hog.py
torch_hog-0.0.1.dist-info/METADATA
torch_hog-0.0.1.dist-info/WHEEL
torch_hog-0.0.1.dist-info/licenses/LICENSE
torch_hog-0.0.1.dist-info/RECORD
