Metadata-Version: 2.4
Name: torch-hog
Version: 0.0.1
Summary: Non Official PyTorch Implementation of the HoG Descriptor
Project-URL: Homepage, https://github.com/wamitw/torch-hog
Author: Amit Abe
License: MIT
License-File: LICENSE
Keywords: classic computer vision,feature extraction,histogram of gradients,hog,hog descriptor,hog feature descriptor,hog feature extraction,pytorch,torch,torch-hog,torchvision
Classifier: Intended Audience :: Science/Research
Classifier: License :: OSI Approved :: MIT License
Classifier: Programming Language :: Python :: 3
Requires-Python: >=3.8
Requires-Dist: einops
Requires-Dist: kornia
Requires-Dist: torch
Requires-Dist: torchvision
